aionanoleaf2/__init__.py
aionanoleaf2/events.py
aionanoleaf2/exceptions.py
aionanoleaf2/layout.py
aionanoleaf2/nanoleaf.py
aionanoleaf2/typing.py
aionanoleaf2-1.0.2.dist-info/licenses/LICENSE
aionanoleaf2-1.0.2.dist-info/METADATA
aionanoleaf2-1.0.2.dist-info/WHEEL
aionanoleaf2-1.0.2.dist-info/top_level.txt
aionanoleaf2-1.0.2.dist-info/RECORD
