Metadata-Version: 2.4
Name: aionanoleaf2
Version: 1.0.2
Summary: Async Python package for the Nanoleaf API that replaces aioNanoleaf.
Home-page: https://github.com/loebi-ch/aionanoleaf2
Author: loebi-ch
Author-email: andy@slyweb.ch
License: LGPLv3+
Project-URL: Bug Tracker, https://github.com/loebi-ch/aionanoleaf2/issues
Project-URL: Source Code, https://github.com/loebi-ch/aionanoleaf2
Project-URL: Documentation, https://github.com/loebi-ch/aionanoleaf/blob/master/README.md
Keywords: nanoleaf api canvas shapes elements light panels strips essentials 4d emersion
Classifier: Programming Language :: Python :: 3
Classifier: License :: OSI Approved :: GNU Lesser General Public License v3 or later (LGPLv3+)
Classifier: Operating System :: OS Independent
Classifier: Development Status :: 4 - Beta
Classifier: Intended Audience :: Developers
Classifier: Natural Language :: English
Classifier: Topic :: Home Automation
Classifier: Typing :: Typed
Requires-Python: >=3.8
License-File: LICENSE
Requires-Dist: aiohttp
Dynamic: author
Dynamic: author-email
Dynamic: classifier
Dynamic: description
Dynamic: description-content-type
Dynamic: home-page
Dynamic: keywords
Dynamic: license
Dynamic: license-file
Dynamic: project-url
Dynamic: requires-dist
Dynamic: requires-python
Dynamic: summary
